rtl/timer.v
module timer #(
    parameter clocks_per_sample = 5
)(
    input clk,
    input reset,
    output reg sample_tick
);

reg [2:0] counter;
    
always@(posedge clk) begin
    
    if (reset) begin
        sample_tick <= 0;
        counter <= 0;
    end

    else if (counter == clocks_per_sample - 1) begin
        sample_tick <= 1;
        counter <= 0;
    end
    
    else begin
        sample_tick <= 0;
        counter <= counter + 1;
    end 


end
 
endmodule

tb/timer_tb.v
`timescale 1ns/1ps

module timer_tb;

reg clk;
reg reset;
wire sample_tick;
    
timer uut(
    .clk(clk),
    .reset(reset),
    .sample_tick(sample_tick)
);

initial begin
    clk = 0;
end

always begin
    #5 clk = ~clk;
end

initial begin
    reset = 1;

    #12;
    reset = 0;

    #100;
    $finish;
end

initial begin
    $dumpfile("timer.vcd");
    $dumpvars(0, timer_tb);
end

endmodule

timer.vcd
$date
	Sun Aug 30 19:45:22 2026
$end
$version
	Icarus Verilog
$end
$timescale
	1ps
$end
$scope module timer_tb $end
$var wire 1 ! sample_tick $end
$var reg 1 " clk $end
$var reg 1 # reset $end
$scope module uut $end
$var wire 1 " clk $end
$var wire 1 # reset $end
$var parameter 32 $ clocks_per_sample $end
$var reg 3 % counter [2:0] $end
$var reg 1 ! sample_tick $end
$upscope $end
$upscope $end
$enddefinitions $end
$comment Show the parameter values. $end
$dumpall
b101 $
$end
#0
$dumpvars
bx %
1#
0"
x!
$end
#5000
b0 %
0!
1"
#10000
0"
#12000
0#
#15000
b1 %
1"
#20000
0"
#25000
b10 %
1"
#30000
0"
#35000
b11 %
1"
#40000
0"
#45000
b100 %
1"
#50000
0"
#55000
b0 %
1!
1"
#60000
0"
#65000
b1 %
0!
1"
#70000
0"
#75000
b10 %
1"
#80000
0"
#85000
b11 %
1"
#90000
0"
#95000
b100 %
1"
#100000
0"
#105000
b0 %
1!
1"
